[
  {
    "20201118": 20201118,
    "工业园区": "工业园区",
    "双湖": "双湖",
    "高尔夫花园": "仁恒双湖湾",
    "46173元/m2": "71583元/m2",
    "92套在售二手房": "62套在售二手房"
  },
  {
    "20201118": 20201118,
    "工业园区": "工业园区",
    "双湖": "双湖",
    "高尔夫花园": "晋合水巷邻里",
    "46173元/m2": "57962元/m2",
    "92套在售二手房": "3套在售二手房"
  },
  {
    "20201118": 20201118,
    "工业园区": "工业园区",
    "双湖": "双湖",
    "高尔夫花园": "城邦花园东区",
    "46173元/m2": "46548元/m2",
    "92套在售二手房": "82套在售二手房"
  },
  {
    "20201118": 20201118,
    "工业园区": "工业园区",
    "双湖": "双湖",
    "高尔夫花园": "融创苏州桃花源",
    "46173元/m2": "53088元/m2",
    "92套在售二手房": "13套在售二手房"
  },
  {
    "20201118": 20201118,
    "工业园区": "工业园区",
    "双湖": "双湖",
    "高尔夫花园": "荣域花园",
    "46173元/m2": "56583元/m2",
    "92套在售二手房": "43套在售二手房"
  },
  {
    "20201118": 20201118,
    "工业园区": "工业园区",
    "双湖": "双湖",
    "高尔夫花园": "九龙仓国宾一号",
    "46173元/m2": "84988元/m2",
    "92套在售二手房": "15套在售二手房"
  },
  {
    "20201118": 20201118,
    "工业园区": "工业园区",
    "双湖": "双湖",
    "高尔夫花园": "中海御湖熙岸西区",
    "46173元/m2": "62295元/m2",
    "92套在售二手房": "29套在售二手房"
  },
  {
    "20201118": 20201118,
    "工业园区": "工业园区",
    "双湖": "双湖",
    "高尔夫花园": "城邦花园西区",
    "46173元/m2": "42769元/m2",
    "92套在售二手房": "54套在售二手房"
  },
  {
    "20201118": 20201118,
    "工业园区": "工业园区",
    "双湖": "双湖",
    "高尔夫花园": "中海御湖熙岸东区",
    "46173元/m2": "61930元/m2",
    "92套在售二手房": "15套在售二手房"
  },
  {
    "20201118": 20201118,
    "工业园区": "工业园区",
    "双湖": "双湖",
    "高尔夫花园": "怡和花园",
    "46173元/m2": "58517元/m2",
    "92套在售二手房": "24套在售二手房"
  },
  {
    "20201118": 20201118,
    "工业园区": "工业园区",
    "双湖": "双湖",
    "高尔夫花园": "仁恒海和院",
    "46173元/m2": "78204元/m2",
    "92套在售二手房": "7套在售二手房"
  },
  {
    "20201118": 20201118,
    "工业园区": "工业园区",
    "双湖": "双湖",
    "高尔夫花园": "和乔丽晶",
    "46173元/m2": "42700元/m2",
    "92套在售二手房": "28套在售二手房"
  },
  {
    "20201118": 20201118,
    "工业园区": "工业园区",
    "双湖": "双湖",
    "高尔夫花园": "世茂铜雀台雅院",
    "46173元/m2": "64677元/m2",
    "92套在售二手房": "13套在售二手房"
  },
  {
    "20201118": 20201118,
    "工业园区": "工业园区",
    "双湖": "双湖",
    "高尔夫花园": "苏州御园",
    "46173元/m2": "83882元/m2",
    "92套在售二手房": "5套在售二手房"
  },
  {
    "20201118": 20201118,
    "工业园区": "工业园区",
    "双湖": "双湖",
    "高尔夫花园": "湖滨四季",
    "46173元/m2": "101986元/m2",
    "92套在售二手房": "1套在售二手房"
  },
  {
    "20201118": 20201118,
    "工业园区": "工业园区",
    "双湖": "双湖",
    "高尔夫花园": "水云居西区",
    "46173元/m2": "59210元/m2",
    "92套在售二手房": "31套在售二手房"
  },
  {
    "20201118": 20201118,
    "工业园区": "工业园区",
    "双湖": "双湖",
    "高尔夫花园": "名湖花园（工业园区）",
    "46173元/m2": "53334元/m2",
    "92套在售二手房": "15套在售二手房"
  },
  {
    "20201118": 20201118,
    "工业园区": "工业园区",
    "双湖": "双湖",
    "高尔夫花园": "观棠",
    "46173元/m2": "73371元/m2",
    "92套在售二手房": "6套在售二手房"
  },
  {
    "20201118": 20201118,
    "工业园区": "工业园区",
    "双湖": "双湖",
    "高尔夫花园": "金水湾",
    "46173元/m2": "59102元/m2",
    "92套在售二手房": "1套在售二手房"
  },
  {
    "20201118": 20201118,
    "工业园区": "工业园区",
    "双湖": "双湖",
    "高尔夫花园": "水墨江南一期",
    "46173元/m2": "60308元/m2",
    "92套在售二手房": "4套在售二手房"
  },
  {
    "20201118": 20201118,
    "工业园区": "工业园区",
    "双湖": "双湖",
    "高尔夫花园": "水云居东区",
    "46173元/m2": "56993元/m2",
    "92套在售二手房": "3套在售二手房"
  },
  {
    "20201118": 20201118,
    "工业园区": "工业园区",
    "双湖": "双湖",
    "高尔夫花园": "建屋乐活城",
    "46173元/m2": "42204元/m2",
    "92套在售二手房": "26套在售二手房"
  },
  {
    "20201118": 20201118,
    "工业园区": "工业园区",
    "双湖": "双湖",
    "高尔夫花园": "中海世家",
    "46173元/m2": "80122元/m2",
    "92套在售二手房": "2套在售二手房"
  },
  {
    "20201118": 20201118,
    "工业园区": "工业园区",
    "双湖": "双湖",
    "高尔夫花园": "仁恒PARK",
    "46173元/m2": "45275元/m2",
    "92套在售二手房": "6套在售二手房"
  },
  {
    "20201118": 20201118,
    "工业园区": "工业园区",
    "双湖": "双湖",
    "高尔夫花园": "水墨江南二期",
    "46173元/m2": "49834元/m2",
    "92套在售二手房": "9套在售二手房"
  },
  {
    "20201118": 20201118,
    "工业园区": "工业园区",
    "双湖": "双湖",
    "高尔夫花园": "李公堤国际风情商业水街",
    "46173元/m2": "暂无",
    "92套在售二手房": "0套在售二手房"
  },
  {
    "20201118": 20201118,
    "工业园区": "工业园区",
    "双湖": "双湖",
    "高尔夫花园": "大湖城邦商业街",
    "46173元/m2": "12371元/m2",
    "92套在售二手房": "1套在售二手房\n"
  }
]
