[
  {
    "20201118": 20201118,
    "吴中": "吴中",
    "越溪": "越溪",
    "石湖华城": "石湖之韵",
    "24484元/m2": "24597元/m2",
    "103套在售二手房": "60套在售二手房"
  },
  {
    "20201118": 20201118,
    "吴中": "吴中",
    "越溪": "越溪",
    "石湖华城": "新城石湖公馆",
    "24484元/m2": "26056元/m2",
    "103套在售二手房": "77套在售二手房"
  },
  {
    "20201118": 20201118,
    "吴中": "吴中",
    "越溪": "越溪",
    "石湖华城": "景瑞御江山",
    "24484元/m2": "25460元/m2",
    "103套在售二手房": "116套在售二手房"
  },
  {
    "20201118": 20201118,
    "吴中": "吴中",
    "越溪": "越溪",
    "石湖华城": "锦和加州北区",
    "24484元/m2": "24179元/m2",
    "103套在售二手房": "41套在售二手房"
  },
  {
    "20201118": 20201118,
    "吴中": "吴中",
    "越溪": "越溪",
    "石湖华城": "石湖华城湖郡华庭",
    "24484元/m2": "24700元/m2",
    "103套在售二手房": "29套在售二手房"
  },
  {
    "20201118": 20201118,
    "吴中": "吴中",
    "越溪": "越溪",
    "石湖华城": "越湖花园",
    "24484元/m2": "19795元/m2",
    "103套在售二手房": "34套在售二手房"
  },
  {
    "20201118": 20201118,
    "吴中": "吴中",
    "越溪": "越溪",
    "石湖华城": "文溪花苑",
    "24484元/m2": "18099元/m2",
    "103套在售二手房": "15套在售二手房"
  },
  {
    "20201118": 20201118,
    "吴中": "吴中",
    "越溪": "越溪",
    "石湖华城": "石湖金钻",
    "24484元/m2": "10480元/m2",
    "103套在售二手房": "25套在售二手房"
  },
  {
    "20201118": 20201118,
    "吴中": "吴中",
    "越溪": "越溪",
    "石湖华城": "锦悦苑",
    "24484元/m2": "23094元/m2",
    "103套在售二手房": "15套在售二手房"
  },
  {
    "20201118": 20201118,
    "吴中": "吴中",
    "越溪": "越溪",
    "石湖华城": "蓝光可可蜜园",
    "24484元/m2": "29149元/m2",
    "103套在售二手房": "34套在售二手房"
  },
  {
    "20201118": 20201118,
    "吴中": "吴中",
    "越溪": "越溪",
    "石湖华城": "和昌熙溪里",
    "24484元/m2": "30133元/m2",
    "103套在售二手房": "44套在售二手房"
  },
  {
    "20201118": 20201118,
    "吴中": "吴中",
    "越溪": "越溪",
    "石湖华城": "南溪苑",
    "24484元/m2": "20053元/m2",
    "103套在售二手房": "15套在售二手房"
  },
  {
    "20201118": 20201118,
    "吴中": "吴中",
    "越溪": "越溪",
    "石湖华城": "石湖天玺",
    "24484元/m2": "27859元/m2",
    "103套在售二手房": "31套在售二手房"
  },
  {
    "20201118": 20201118,
    "吴中": "吴中",
    "越溪": "越溪",
    "石湖华城": "溪东新村三区",
    "24484元/m2": "19161元/m2",
    "103套在售二手房": "22套在售二手房"
  },
  {
    "20201118": 20201118,
    "吴中": "吴中",
    "越溪": "越溪",
    "石湖华城": "翠湖湾",
    "24484元/m2": "23496元/m2",
    "103套在售二手房": "20套在售二手房"
  },
  {
    "20201118": 20201118,
    "吴中": "吴中",
    "越溪": "越溪",
    "石湖华城": "绿景苏州公馆",
    "24484元/m2": "15350元/m2",
    "103套在售二手房": "38套在售二手房"
  },
  {
    "20201118": 20201118,
    "吴中": "吴中",
    "越溪": "越溪",
    "石湖华城": "石湖华城公寓",
    "24484元/m2": "19074元/m2",
    "103套在售二手房": "4套在售二手房"
  },
  {
    "20201118": 20201118,
    "吴中": "吴中",
    "越溪": "越溪",
    "石湖华城": "石湖华城湖郡",
    "24484元/m2": "31665元/m2",
    "103套在售二手房": "8套在售二手房"
  },
  {
    "20201118": 20201118,
    "吴中": "吴中",
    "越溪": "越溪",
    "石湖华城": "嘉盛花园",
    "24484元/m2": "20282元/m2",
    "103套在售二手房": "20套在售二手房"
  },
  {
    "20201118": 20201118,
    "吴中": "吴中",
    "越溪": "越溪",
    "石湖华城": "金辉我的日子",
    "24484元/m2": "26225元/m2",
    "103套在售二手房": "21套在售二手房"
  },
  {
    "20201118": 20201118,
    "吴中": "吴中",
    "越溪": "越溪",
    "石湖华城": "尧南花苑",
    "24484元/m2": "15289元/m2",
    "103套在售二手房": "3套在售二手房"
  },
  {
    "20201118": 20201118,
    "吴中": "吴中",
    "越溪": "越溪",
    "石湖华城": "南苏州中央鼎寓",
    "24484元/m2": "9483元/m2",
    "103套在售二手房": "14套在售二手房"
  },
  {
    "20201118": 20201118,
    "吴中": "吴中",
    "越溪": "越溪",
    "石湖华城": "美田青春花园",
    "24484元/m2": "10771元/m2",
    "103套在售二手房": "16套在售二手房"
  },
  {
    "20201118": 20201118,
    "吴中": "吴中",
    "越溪": "越溪",
    "石湖华城": "新思家园",
    "24484元/m2": "16885元/m2",
    "103套在售二手房": "7套在售二手房"
  },
  {
    "20201118": 20201118,
    "吴中": "吴中",
    "越溪": "越溪",
    "石湖华城": "锦和加州南区",
    "24484元/m2": "22017元/m2",
    "103套在售二手房": "3套在售二手房"
  },
  {
    "20201118": 20201118,
    "吴中": "吴中",
    "越溪": "越溪",
    "石湖华城": "简之韵花园",
    "24484元/m2": "24380元/m2",
    "103套在售二手房": "2套在售二手房"
  },
  {
    "20201118": 20201118,
    "吴中": "吴中",
    "越溪": "越溪",
    "石湖华城": "海馨花园",
    "24484元/m2": "27636元/m2",
    "103套在售二手房": "5套在售二手房"
  },
  {
    "20201118": 20201118,
    "吴中": "吴中",
    "越溪": "越溪",
    "石湖华城": "越溪庭院",
    "24484元/m2": "22979元/m2",
    "103套在售二手房": "0套在售二手房"
  },
  {
    "20201118": 20201118,
    "吴中": "吴中",
    "越溪": "越溪",
    "石湖华城": "溪东新村四区",
    "24484元/m2": "18387元/m2",
    "103套在售二手房": "1套在售二手房\n"
  }
]
